safe_pip_upgrade/__init__.py
safe_pip_upgrade/config.py
safe_pip_upgrade/pip_upgrade.py
safe_pip_upgrade/pypi.py
safe_pip_upgrade/requirements_file.py
safe_pip_upgrade/core/__init__.py
safe_pip_upgrade/core/packages.py
safe_pip_upgrade/core/upgrade.py
safe_pip_upgrade/runners/compose.py
safe_pip_upgrade-0.0.5.dist-info/LICENSE
safe_pip_upgrade-0.0.5.dist-info/METADATA
safe_pip_upgrade-0.0.5.dist-info/WHEEL
safe_pip_upgrade-0.0.5.dist-info/entry_points.txt
safe_pip_upgrade-0.0.5.dist-info/top_level.txt
safe_pip_upgrade-0.0.5.dist-info/RECORD
