Metadata-Version: 2.1
Name: safe-pip-upgrade
Version: 0.0.5
Summary: Pip safe auto-upgrade
Home-page: https://github.com/VVyacheslav/safe-pip-upgrade
Author: Vyacheslav Vertliba
Author-email: vertliba.vv@gmail.com
License: MIT
Platform: UNKNOWN
Requires-Dist: requests
Requires-Dist: pip
Requires-Dist: packaging
